[
  {
    "StockTicker":"NDX   251121C25200000",
    "Weightings":-0.68,
    "Expiry_Date":"2025-11-21",
    "Option_Type":"C",
    "Strike_Price":25200.0,
    "OpeningPrice":23738.67,
    "Contracts":712.0,
    "ForgoneGain":0.0,
    "ForgoneGainPct":0.0,
    "TotalBaseMV":5409798261.2299995422
  },
  {
    "StockTicker":"NDX   251121C25600000",
    "Weightings":-0.45,
    "Expiry_Date":"2025-11-21",
    "Option_Type":"C",
    "Strike_Price":25600.0,
    "OpeningPrice":23738.67,
    "Contracts":712.0,
    "ForgoneGain":0.0,
    "ForgoneGainPct":0.0,
    "TotalBaseMV":5409798261.2299995422
  }
]